pygentic_ai/__init__.py
pygentic_ai/engines/__init__.py
pygentic_ai/engines/base.py
pygentic_ai/engines/guardrails.py
pygentic_ai/engines/reasoning.py
pygentic_ai/engines/routers.py
pygentic_ai/engines/translators.py
pygentic_ai/manager.py
pygentic_ai/prompts/__init__.py
pygentic_ai/prompts/agent_prompts.py
pygentic_ai/prompts/worker_prompts.py
pygentic_ai/py.typed
pygentic_ai/schemas/__init__.py
pygentic_ai/schemas/agent.py
pygentic_ai/schemas/messages.py
pygentic_ai/static/__init__.py
pygentic_ai/static/default_msgs.py
pygentic_ai/tools/__init__.py
pygentic_ai/tools/dateutils.py
pygentic_ai/tools/tool_registry.py
pygentic_ai/utils/__init__.py
pygentic_ai/utils/llm_vendor.py
pygentic_ai/workflows/__init__.py
pygentic_ai/workflows/agent_workflow.py
pygentic_ai/workflows/nodes/__init__.py
pygentic_ai/workflows/nodes/base.py
pygentic_ai/workflows/nodes/generation.py
pygentic_ai/workflows/nodes/guardrails.py
pygentic_ai/workflows/nodes/refusal.py
pygentic_ai/workflows/nodes/routing.py
pygentic_ai/workflows/nodes/translation.py
pygentic_ai/workflows/state.py
pygentic_ai-0.1.0.post1.dist-info/WHEEL
pygentic_ai-0.1.0.post1.dist-info/METADATA
pygentic_ai-0.1.0.post1.dist-info/RECORD
