Metadata-Version: 2.3
Name: pygentic-ai
Version: 0.1.0.post1
Summary: A meta-framework for building agentic workflows with Pydantic AI
Keywords: ai,agents,mcp,llm,pydantic,pydantic-ai,fastmcp,workflow,automation,openai,anthropic,meta-framework
Author: Sebastian Kalisz
Author-email: Sebastian Kalisz <23085519+KaliszS@users.noreply.github.com>
License: MIT
Classifier: Development Status :: 3 - Alpha
Classifier: Intended Audience :: Developers
Classifier: License :: OSI Approved :: MIT License
Classifier: Operating System :: OS Independent
Classifier: Programming Language :: Python :: 3
Classifier: Programming Language :: Python :: 3.12
Classifier: Programming Language :: Python :: 3.13
Classifier: Programming Language :: Python :: 3.14
Classifier: Topic :: Scientific/Engineering :: Artificial Intelligence
Classifier: Topic :: Software Development :: Libraries :: Python Modules
Classifier: Typing :: Typed
Requires-Dist: pydantic-ai>=1.51.0
Requires-Dist: pydantic-settings>=2.12.0
Maintainer: Sebastian Kalisz
Maintainer-email: Sebastian Kalisz <23085519+KaliszS@users.noreply.github.com>
Requires-Python: >=3.12
Project-URL: Changelog, https://github.com/the-momentum/pygentic-ai/blob/main/CHANGELOG.md
Project-URL: Documentation, https://github.com/the-momentum/pygentic-ai#readme
Project-URL: Homepage, https://github.com/the-momentum/pygentic-ai
Project-URL: Issues, https://github.com/the-momentum/pygentic-ai/issues
Project-URL: Repository, https://github.com/the-momentum/pygentic-ai.git
